candella_sdk/__init__.py
candella_sdk/__main__.py
candella_sdk/cli.py
candella_sdk/sdk.py
candella_sdk-1.0.0a1.dist-info/entry_points.txt
candella_sdk-1.0.0a1.dist-info/LICENSE
candella_sdk-1.0.0a1.dist-info/WHEEL
candella_sdk-1.0.0a1.dist-info/METADATA
candella_sdk-1.0.0a1.dist-info/RECORD
